kumaraswamy/__init__.py
kumaraswamy/kumaraswamy.py
kumaraswamy-0.2.dist-info/LICENSE
kumaraswamy-0.2.dist-info/METADATA
kumaraswamy-0.2.dist-info/WHEEL
kumaraswamy-0.2.dist-info/top_level.txt
kumaraswamy-0.2.dist-info/RECORD
