Metadata-Version: 2.1
Name: kumaraswamy
Version: 0.2
Summary: Implementation of the Kumaraswamy distribution
Home-page: https://github.com/j-faria/Kumaraswamy
Author: João Faria
Author-email: joao.faria@astro.up.pt
License: MIT
Platform: UNKNOWN
Classifier: Programming Language :: Python :: 3
Classifier: License :: OSI Approved :: MIT License
Classifier: Operating System :: OS Independent
